src/__init__.py
src/cli.py
src/client.py
src/main.py
src/utils.py
mcp_omni_connect-0.1.0.dist-info/METADATA
mcp_omni_connect-0.1.0.dist-info/WHEEL
mcp_omni_connect-0.1.0.dist-info/entry_points.txt
mcp_omni_connect-0.1.0.dist-info/licenses/LICENSE
mcp_omni_connect-0.1.0.dist-info/RECORD
