Metadata-Version: 2.4
Name: mcp-omni-connect
Version: 0.1.0
Summary: Universal MCP Client with multi-transport support and LLM-powered tool routing
Project-URL: Homepage, https://github.com/Abiorh001/mcp_omni_connect
Project-URL: Repository, https://github.com/Abiorh001/mcp_omni_connect.git
Project-URL: Issues, https://github.com/Abiorh001/mcp_omni_connect/issues
Author-email: Abiola Adeshina <abioladedayo1993@gmail.com>
License: MIT License
License-File: LICENSE
Keywords: ai,cli,llm,mcp,smithery
Classifier: Development Status :: 4 - Beta
Classifier: Intended Audience :: Developers
Classifier: License :: OSI Approved :: MIT License
Classifier: Programming Language :: Python :: 3
Classifier: Programming Language :: Python :: 3.12
Requires-Python: >=3.12
Requires-Dist: anyio>=4.2.0
Requires-Dist: httpx-sse>=0.4.0
Requires-Dist: httpx>=0.26.0
Requires-Dist: pydantic>=2.6.0
Requires-Dist: rich>=13.7.0
Requires-Dist: websockets>=12.0
